LICENSE
MANIFEST.in
README.md
pynvml_amd_windows.pth
pyproject.toml
requirements.txt
pynvml_amd_windows/__init__.py
pynvml_amd_windows/pynvml.py
pynvml_amd_windows.egg-info/PKG-INFO
pynvml_amd_windows.egg-info/SOURCES.txt
pynvml_amd_windows.egg-info/dependency_links.txt
pynvml_amd_windows.egg-info/requires.txt
pynvml_amd_windows.egg-info/top_level.txt