Metadata-Version: 2.4
Name: pynvml_amd_windows
Version: 1.0.10
Summary: pynvml-compatible library for AMD GPUs on Windows
Author-email: sfinktah <sfinktah@github.spamtrak.org>
License-Expression: MIT
Project-URL: Bug Reports, https://github.com/sfinktah/pynvml-amd-windows/issues
Project-URL: Source, https://github.com/sfinktah/pynvml-amd-windows
Keywords: amd,gpu,nvidia,pynvml,adlx,crystools,comfyui,windows
Classifier: Development Status :: 4 - Beta
Classifier: Intended Audience :: Developers
Classifier: Operating System :: Microsoft :: Windows
Classifier: Programming Language :: Python :: 3
Classifier: Programming Language :: Python :: 3.7
Classifier: Programming Language :: Python :: 3.8
Classifier: Programming Language :: Python :: 3.9
Classifier: Programming Language :: Python :: 3.10
Classifier: Programming Language :: Python :: 3.11
Classifier: Programming Language :: Python :: 3.12
Classifier: Topic :: System :: Hardware
Classifier: Topic :: System :: Monitoring
Classifier: Topic :: Software Development :: Libraries :: Python Modules
Requires-Python: >=3.7
License-File: LICENSE
Requires-Dist: adlxpybind>=1.4.2
Dynamic: license-file
